campbot/__init__.py
campbot/__main__.py
campbot/checkers.py
campbot/core.py
campbot/differ.py
campbot/dump.py
campbot/objects.py
campbot/utils.py
campbot/version.py
campbot/processors/__init__.py
campbot/processors/bbcode.py
campbot/processors/cleaners.py
campbot/processors/core.py
campbot/processors/ltagmigrator.py
tests/__init__.py
tests/fixtures.py
tests/test_differ.py
tests/test_miscs.py
tests/test_processors.py
campbot-2.0.0.dist-info/LICENSE.txt
campbot-2.0.0.dist-info/METADATA
campbot-2.0.0.dist-info/WHEEL
campbot-2.0.0.dist-info/entry_points.txt
campbot-2.0.0.dist-info/top_level.txt
campbot-2.0.0.dist-info/RECORD
