Metadata-Version: 2.1
Name: campbot
Version: 2.0.0
Summary: Package for automatic edition of camptocamp.org
Home-page: http://github.com/c2corg/CampBot
Author: Charles de Beauchesne
Author-email: charles.de.beauchesne@gmail.com
License: WTFPL
Platform: UNKNOWN
Classifier: Programming Language :: Python
Classifier: Development Status :: 3 - Alpha
Classifier: License :: OSI Approved
Classifier: Natural Language :: English
Classifier: Operating System :: OS Independent
Classifier: Programming Language :: Python :: 3.6
Classifier: Programming Language :: Python :: 3.7
Classifier: Programming Language :: Python :: 3.8
Classifier: Programming Language :: Python :: 3.9
Classifier: Programming Language :: Python :: 3.10
Classifier: Topic :: Communications
License-File: LICENSE.txt
Requires-Dist: docopt (==0.6.2)
Requires-Dist: requests (==2.27.1)
Requires-Dist: python-dateutil (==2.8.2)
Requires-Dist: pytz (==2021.3)
